db_auto_interface/__init__.py
db_auto_interface/configure.py
db_auto_interface/core/__init__.py
db_auto_interface/core/db_schema.py
db_auto_interface/core/navigation.py
db_auto_interface/core/universal_db.py
db_auto_interface/ui/__init__.py
db_auto_interface/ui/code_generator.py
db_auto_interface/ui/main_app.py
db_auto_interface/ui/record_form.py
db_auto_interface/ui/table_view.py
db_auto_interface/ui/theme_engine.py
db_auto_interface/ui/widgets.py
db_auto_interface/utils/__init__.py
db_auto_interface-2.0.0.dist-info/licenses/LICENSE
db_auto_interface-2.0.0.dist-info/METADATA
db_auto_interface-2.0.0.dist-info/WHEEL
db_auto_interface-2.0.0.dist-info/entry_points.txt
db_auto_interface-2.0.0.dist-info/top_level.txt
db_auto_interface-2.0.0.dist-info/RECORD
