Metadata-Version: 2.4
Name: db-auto-interface
Version: 2.0.0
Summary: Автоматический генератор desktop интерфейса для PostgreSQL БД
Home-page: https://github.com/yourusername/db_auto_interface
Author: Your Name
Author-email: Your Name <your.email@example.com>
Project-URL: Bug Reports, https://github.com/yourusername/db_auto_interface/issues
Project-URL: Source, https://github.com/yourusername/db_auto_interface
Project-URL: Documentation, https://github.com/yourusername/db_auto_interface#readme
Keywords: database,postgresql,gui,tkinter,crud,interface
Classifier: Development Status :: 4 - Beta
Classifier: Intended Audience :: Developers
Classifier: Intended Audience :: Education
Classifier: Topic :: Database
Classifier: Topic :: Database :: Front-Ends
Classifier: Programming Language :: Python :: 3
Classifier: Programming Language :: Python :: 3.8
Classifier: Programming Language :: Python :: 3.9
Classifier: Programming Language :: Python :: 3.10
Classifier: Programming Language :: Python :: 3.11
Classifier: Programming Language :: Python :: 3.12
Classifier: Operating System :: OS Independent
Requires-Python: >=3.8
License-File: LICENSE
Requires-Dist: psycopg2-binary>=2.9.0
Provides-Extra: dev
Requires-Dist: pytest>=7.0.0; extra == "dev"
Requires-Dist: black>=22.0.0; extra == "dev"
Dynamic: author
Dynamic: home-page
Dynamic: license-file
Dynamic: requires-python
